ng_to_verilog/__init__.py
ng_to_verilog/export.py
ng_to_verilog/load.py
ng_to_verilog/pins_ports_io.py
ng_to_verilog/primitives.py
ng_to_verilog/settings.py
ng_to_verilog/util.py
ng_to_verilog/resources/primitives.json
ng_to_verilog/templates/build.j2
ng_to_verilog/templates/verilogModule.j2
ng_to_verilog-2025.5.10.dist-info/licenses/LICENSE
ng_to_verilog-2025.5.10.dist-info/METADATA
ng_to_verilog-2025.5.10.dist-info/WHEEL
ng_to_verilog-2025.5.10.dist-info/top_level.txt
ng_to_verilog-2025.5.10.dist-info/RECORD
