Metadata-Version: 2.4
Name: ng-to-verilog
Version: 2025.5.10
Summary: Nandgame to Verilog
Author-email: Patrick Cox <patrick.cox@gmail.com>
License: MIT License
Project-URL: Homepage, https://github.com/xocp/ng-to-verilog
Keywords: nandgame,verilog,fpga
Classifier: License :: OSI Approved :: MIT License
Classifier: Programming Language :: Python
Classifier: Programming Language :: Python :: 3
Requires-Python: >=3.9
License-File: LICENSE
Requires-Dist: Jinja2>=3.1.4
Requires-Dist: MarkupSafe>=2.1.5
Provides-Extra: dev
Requires-Dist: pip-tools; extra == "dev"
Requires-Dist: pytest; extra == "dev"
Dynamic: license-file
